README.txt
setup.py
django_pyres/__init__.py
django_pyres/conf.py
django_pyres/core.py
django_pyres/decorators.py
django_pyres/models.py
django_pyres/tests.py
django_pyres/views.py
django_pyres/worker.py
django_pyres.egg-info/PKG-INFO
django_pyres.egg-info/SOURCES.txt
django_pyres.egg-info/dependency_links.txt
django_pyres.egg-info/requires.txt
django_pyres.egg-info/top_level.txt
django_pyres/management/__init__.py
django_pyres/management/commands/__init__.py
django_pyres/management/commands/pyres_manager.py
django_pyres/management/commands/pyres_worker.py