Metadata-Version: 1.0
Name: django-pyres
Version: 0.1.2
Summary: django pyres integration
Home-page: http://github.com/Pyres/django_pyres
Author: Matt George
Author-email: mgeorge@gmail.com
License: MIT
Platform: UNKNOWN
Classifier: Development Status :: 4 - Beta
Classifier: Environment :: Console
Classifier: Intended Audience :: Developers
Classifier: License :: OSI Approved :: MIT License
Classifier: Operating System :: OS Independent
Classifier: Programming Language :: Python
